{
 "SoundBanksInfo": {
  "Platform": "Windows",
  "BasePlatform": "Windows",
  "SchemaVersion": "16",
  "SoundBankVersion": "154",
  "SoundBanks": [
   {
    "Id": "1236374173",
    "Type": "Event",
    "GUID": "{A94E4932-642C-4BC7-BF98-3969FB49BF59}",
    "Language": "SFX",
    "Hash": "{7B10B3F8-23D8-664D-76F5-7B0325AA7128}",
    "ObjectPath": "play_amb_waterfall",
    "ShortName": "play_amb_waterfall",
    "Path": "Event/play_amb_waterfall.bnk",
    "Media": [
     {
      "Id": "244424738",
      "Language": "SFX",
      "Streaming": "false",
      "Location": "Loose",
      "ShortName": "amb_cave_waterfall.wav",
      "Path": "Media/244424738.wem",
      "CachePath": "74/{74C9FE76-676B-C978-9879-22FD896B2ADD}.wem"
     }
    ],
    "Events": [
     {
      "Id": "1236374173",
      "Name": "play_amb_waterfall",
      "ObjectPath": "\\Events\\Ambience\\Cave\\play_amb_waterfall",
      "GUID": "{A94E4932-642C-4BC7-BF98-3969FB49BF59}",
      "Color": "5",
      "DurationType": "OneShot",
      "DurationMin": "236.54596",
      "DurationMax": "236.54596",
      "MediaRefs": [
       {
        "Id": "244424738"
       }
      ]
     }
    ]
   }
  ],
  "FileHash": "{7FB94051-E8CD-21AC-50FF-3D4C21B37B1A}"
 }
}